pymsch/__init__.py
pymsch/py.typed
pymsch/mimex-data/.git
pymsch/mimex-data/README.md
pymsch/mimex-data/data/stable-builtins.txt
pymsch/mimex-data/data/be/mimex-alignments.txt
pymsch/mimex-data/data/be/mimex-block-flags.txt
pymsch/mimex-data/data/be/mimex-blocks.txt
pymsch/mimex-data/data/be/mimex-colors.txt
pymsch/mimex-data/data/be/mimex-commands.txt
pymsch/mimex-data/data/be/mimex-conditions.txt
pymsch/mimex-data/data/be/mimex-contents.txt
pymsch/mimex-data/data/be/mimex-cutscene-actions.txt
pymsch/mimex-data/data/be/mimex-effects.txt
pymsch/mimex-data/data/be/mimex-fetch-types.txt
pymsch/mimex-data/data/be/mimex-graphics-types.txt
pymsch/mimex-data/data/be/mimex-icons.txt
pymsch/mimex-data/data/be/mimex-items.txt
pymsch/mimex-data/data/be/mimex-laccess.txt
pymsch/mimex-data/data/be/mimex-layers.txt
pymsch/mimex-data/data/be/mimex-liquids.txt
pymsch/mimex-data/data/be/mimex-locate.txt
pymsch/mimex-data/data/be/mimex-logic-rules.txt
pymsch/mimex-data/data/be/mimex-marker-control.txt
pymsch/mimex-data/data/be/mimex-markers.txt
pymsch/mimex-data/data/be/mimex-message-types.txt
pymsch/mimex-data/data/be/mimex-operations.txt
pymsch/mimex-data/data/be/mimex-radar-sorts.txt
pymsch/mimex-data/data/be/mimex-radar-targets.txt
pymsch/mimex-data/data/be/mimex-sounds.txt
pymsch/mimex-data/data/be/mimex-status-effects.txt
pymsch/mimex-data/data/be/mimex-unit-control.txt
pymsch/mimex-data/data/be/mimex-units.txt
pymsch/mimex-data/data/be/mimex-vars.txt
pymsch/mimex-data/data/be/mimex-weathers.txt
pymsch/mimex-data/data/v126.2/mimex-block-flags.txt
pymsch/mimex-data/data/v126.2/mimex-blocks.txt
pymsch/mimex-data/data/v126.2/mimex-colors.txt
pymsch/mimex-data/data/v126.2/mimex-conditions.txt
pymsch/mimex-data/data/v126.2/mimex-contents.txt
pymsch/mimex-data/data/v126.2/mimex-graphics-types.txt
pymsch/mimex-data/data/v126.2/mimex-icons.txt
pymsch/mimex-data/data/v126.2/mimex-items.txt
pymsch/mimex-data/data/v126.2/mimex-laccess.txt
pymsch/mimex-data/data/v126.2/mimex-liquids.txt
pymsch-0.0.15.dist-info/METADATA
pymsch-0.0.15.dist-info/WHEEL
pymsch-0.0.15.dist-info/licenses/LICENSE
pymsch-0.0.15.dist-info/RECORD
