Metadata-Version: 2.4
Name: pymsch
Version: 0.0.15
Summary: A package for creating mindustry schematic files
Project-URL: Source, https://github.com/SkyeTheFoxyFox/pymsch
Author: skyethefoxyfox
License-File: LICENSE
Classifier: License :: OSI Approved :: MIT License
Classifier: Operating System :: OS Independent
Classifier: Programming Language :: Python :: 3
Requires-Python: >=3.10
Requires-Dist: pyperclip
